[
  {
    "email": "wayne.erradu@unityincommunity.org.za",
    "fullName": "Wayne Erradu",
    "nickname": "",
    "bio": "",
    "dateOfBirth": "",
    "physicalAddress": "",
    "mobileNumber": "",
    "status": "active",
    "avatarImage": "",
    "privateNotes": "",
    "delegateEmail": ""
  },
  {
    "email": "hello@unityincommunity.org.za",
    "fullName": "Hello Mailbox",
    "nickname": "",
    "bio": "",
    "dateOfBirth": "",
    "physicalAddress": "",
    "mobileNumber": "",
    "status": "active",
    "avatarImage": "",
    "privateNotes": "",
    "delegateEmail": ""
  },
  {
    "email": "sarah.basson@unityincommunity.org.za",
    "fullName": "Sarah Basson",
    "nickname": "",
    "bio": "",
    "dateOfBirth": "",
    "physicalAddress": "",
    "mobileNumber": "",
    "status": "active",
    "avatarImage": "",
    "privateNotes": "",
    "delegateEmail": ""
  },
  {
    "email": "marvin.naicker@unityincommunity.org.za",
    "fullName": "Marvin Naicker",
    "nickname": "",
    "bio": "",
    "dateOfBirth": "",
    "physicalAddress": "",
    "mobileNumber": "",
    "status": "active",
    "avatarImage": "",
    "privateNotes": "",
    "delegateEmail": ""
  },
  {
    "email": "nomasonto.ncgungane@unityincommunity.org.za",
    "fullName": "Nomasonto Ncgungane",
    "nickname": "",
    "bio": "",
    "dateOfBirth": "",
    "physicalAddress": "",
    "mobileNumber": "",
    "status": "active",
    "avatarImage": "",
    "privateNotes": "",
    "delegateEmail": ""
  },
  {
    "email": "bronwynne.batstone@unityincommunity.org.za",
    "fullName": "Bronwynne Batstone",
    "nickname": "",
    "bio": "",
    "dateOfBirth": "",
    "physicalAddress": "",
    "mobileNumber": "",
    "status": "active",
    "avatarImage": "",
    "privateNotes": "",
    "delegateEmail": ""
  },
  {
    "email": "vishal.kanhai@unityincommunity.org.za",
    "fullName": "Vishal Kanhai",
    "nickname": "",
    "bio": "",
    "dateOfBirth": "",
    "physicalAddress": "",
    "mobileNumber": "",
    "status": "active",
    "avatarImage": "",
    "privateNotes": "",
    "delegateEmail": ""
  },
  {
    "email": "superadmin@unityincommunity.org.za",
    "fullName": "Local Super Admin",
    "nickname": "DevOps",
    "bio": "",
    "dateOfBirth": "",
    "physicalAddress": "",
    "mobileNumber": "",
    "status": "active",
    "avatarImage": "",
    "privateNotes": "",
    "delegateEmail": ""
  }
]
